controller/__init__.py
controller/controller.py
dao/__init__.py
dao/baseDao.py
dao/instDao.py
dao/instExtraDao.py
dao/optDao.py
dao/synonymsDao.py
dao/entity/__init__.py
dao/entity/inst.py
dao/entity/instExtra.py
dao/entity/opt.py
dao/entity/synonym.py
data/__init__.py
data/collection.py
data/imexport.py
data/parse.py
data/process.py
data/storage.py
logic/__init__.py
logic/complement.py
logic/terminal.py
logic/tfidf.py
view/__init__.py
view/cli.py
view/display.py
view/terminal.py
view/ui.py
OSTutortest1-1.0.4.dist-info/METADATA
OSTutortest1-1.0.4.dist-info/WHEEL
OSTutortest1-1.0.4.dist-info/entry_points.txt
OSTutortest1-1.0.4.dist-info/top_level.txt
OSTutortest1-1.0.4.dist-info/RECORD
